{"routes": [{"name": ["String", "Vancouver"], "neighbours": [{"city": ["String", "Calgary"], "routeColor": ["String", "wild"], "routeLength": ["Integer", 3]}, {"city": ["String", "Seattle"], "routeColor": ["String", "wild"], "routeLength": ["Integer", 1]}]}, {"name": ["String", "Calgary"], "neighbours": [{"city": ["String", "Vancouver"], "routeColor": ["String", "wild"], "routeLength": ["Integer", 3]}, {"city": ["String", "Seattle"], "routeColor": ["String", "wild"], "routeLength": ["Integer", 4]}, {"city": ["String", "Helena"], "routeColor": ["String", "wild"], "routeLength": ["Integer", 4]}, {"city": ["String", "Winnipeg"], "routeColor": ["String", "white"], "routeLength": ["Integer", 6]}]}, {"name": ["String", "Winnipeg"], "neighbours": [{"city": ["String", "Calgary"], "routeColor": ["String", "white"], "routeLength": ["Integer", 6]}, {"city": ["String", "Helena"], "routeColor": ["String", "blue"], "routeLength": ["Integer", 4]}, {"city": ["String", "Duluth"], "routeColor": ["String", "black"], "routeLength": ["Integer", 4]}, {"city": ["String", "SaultStMarie"], "routeColor": ["String", "wild"], "routeLength": ["Integer", 6]}]}, {"name": ["String", "SaultStMarie"], "neighbours": [{"city": ["String", "Winnipeg"], "routeColor": ["String", "wild"], "routeLength": ["Integer", 6]}, {"city": ["String", "Duluth"], "routeColor": ["String", "wild"], "routeLength": ["Integer", 3]}, {"city": ["String", "Toronto"], "routeColor": ["String", "wild"], "routeLength": ["Integer", 2]}, {"city": ["String", "Montreal"], "routeColor": ["String", "black"], "routeLength": ["Integer", 5]}]}, {"name": ["String", "Montreal"], "neighbours": [{"city": ["String", "SaultStMarie"], "routeColor": ["String", "black"], "routeLength": ["Integer", 5]}, {"city": ["String", "Toronto"], "routeColor": ["String", "wild"], "routeLength": ["Integer", 3]}, {"city": ["String", "NewYork"], "routeColor": ["String", "blue"], "routeLength": ["Integer", 3]}, {"city": ["String", "Boston"], "routeColor": ["String", "wild"], "routeLength": ["Integer", 2]}]}, {"name": ["String", "Seattle"], "neighbours": [{"city": ["String", "Vancouver"], "routeColor": ["String", "wild"], "routeLength": ["Integer", 1]}, {"city": ["String", "Calgary"], "routeColor": ["String", "wild"], "routeLength": ["Integer", 4]}, {"city": ["String", "Portland"], "routeColor": ["String", "wild"], "routeLength": ["Integer", 1]}, {"city": ["String", "Helena"], "routeColor": ["String", "yellow"], "routeLength": ["Integer", 6]}]}, {"name": ["String", "Portland"], "neighbours": [{"city": ["String", "Seattle"], "routeColor": ["String", "wild"], "routeLength": ["Integer", 1]}, {"city": ["String", "SanFrancisco"], "routeColor": ["String", "purple"], "routeLength": ["Integer", 5]}, {"city": ["String", "SanFrancisco"], "routeColor": ["String", "green"], "routeLength": ["Integer", 5]}, {"city": ["String", "SaltLakeCity"], "routeColor": ["String", "blue"], "routeLength": ["Integer", 6]}]}, {"name": ["String", "SanFrancisco"], "neighbours": [{"city": ["String", "Portland"], "routeColor": ["String", "purple"], "routeLength": ["Integer", 5]}, {"city": ["String", "Portland"], "routeColor": ["String", "green"], "routeLength": ["Integer", 5]}, {"city": ["String", "SaltLakeCity"], "routeColor": ["String", "white"], "routeLength": ["Integer", 5]}, {"city": ["String", "SaltLakeCity"], "routeColor": ["String", "orange"], "routeLength": ["Integer", 5]}, {"city": ["String", "LosAngeles"], "routeColor": ["String", "purple"], "routeLength": ["Integer", 3]}, {"city": ["String", "LosAngeles"], "routeColor": ["String", "yellow"], "routeLength": ["Integer", 3]}]}, {"name": ["String", "SaltLakeCity"], "neighbours": [{"city": ["String", "SanFrancisco"], "routeColor": ["String", "orange"], "routeLength": ["Integer", 5]}, {"city": ["String", "SanFrancisco"], "routeColor": ["String", "white"], "routeLength": ["Integer", 5]}, {"city": ["String", "Portland"], "routeColor": ["String", "blue"], "routeLength": ["Integer", 6]}, {"city": ["String", "Helena"], "routeColor": ["String", "purple"], "routeLength": ["Integer", 3]}, {"city": ["String", "Denver"], "routeColor": ["String", "red"], "routeLength": ["Integer", 3]}, {"city": ["String", "Denver"], "routeColor": ["String", "yellow"], "routeLength": ["Integer", 3]}, {"city": ["String", "LasVegas"], "routeColor": ["String", "orange"], "routeLength": ["Integer", 3]}]}, {"name": ["String", "LosAngeles"], "neighbours": [{"city": ["String", "SanFrancisco"], "routeColor": ["String", "purple"], "routeLength": ["Integer", 3]}, {"city": ["String", "SanFrancisco"], "routeColor": ["String", "yellow"], "routeLength": ["Integer", 3]}, {"city": ["String", "LasVegas"], "routeColor": ["String", "wild"], "routeLength": ["Integer", 2]}, {"city": ["String", "Phoenix"], "routeColor": ["String", "wild"], "routeLength": ["Integer", 3]}, {"city": ["String", "ElPaso"], "routeColor": ["String", "black"], "routeLength": ["Integer", 6]}]}, {"name": ["String", "LasVegas"], "neighbours": [{"city": ["String", "SaltLakeCity"], "routeColor": ["String", "orange"], "routeLength": ["Integer", 3]}, {"city": ["String", "LosAngeles"], "routeColor": ["String", "wild"], "routeLength": ["Integer", 2]}]}, {"name": ["String", "Helena"], "neighbours": [{"city": ["String", "Calgary"], "routeColor": ["String", "wild"], "routeLength": ["Integer", 4]}, {"city": ["String", "SaltLakeCity"], "routeColor": ["String", "purple"], "routeLength": ["Integer", 3]}, {"city": ["String", "Seattle"], "routeColor": ["String", "yellow"], "routeLength": ["Integer", 6]}, {"city": ["String", "Winnipeg"], "routeColor": ["String", "blue"], "routeLength": ["Integer", 4]}, {"city": ["String", "Duluth"], "routeColor": ["String", "orange"], "routeLength": ["Integer", 6]}, {"city": ["String", "Omaha"], "routeColor": ["String", "red"], "routeLength": ["Integer", 5]}, {"city": ["String", "Denver"], "routeColor": ["String", "green"], "routeLength": ["Integer", 4]}]}, {"name": ["String", "Phoenix"], "neighbours": [{"city": ["String", "LosAngeles"], "routeColor": ["String", "wild"], "routeLength": ["Integer", 3]}, {"city": ["String", "Denver"], "routeColor": ["String", "white"], "routeLength": ["Integer", 5]}, {"city": ["String", "SantaFe"], "routeColor": ["String", "wild"], "routeLength": ["Integer", 3]}, {"city": ["String", "ElPaso"], "routeColor": ["String", "wild"], "routeLength": ["Integer", 3]}]}, {"name": ["String", "SantaFe"], "neighbours": [{"city": ["String", "Phoenix"], "routeColor": ["String", "wild"], "routeLength": ["Integer", 3]}, {"city": ["String", "Denver"], "routeColor": ["String", "wild"], "routeLength": ["Integer", 2]}, {"city": ["String", "OklahomaCity"], "routeColor": ["String", "blue"], "routeLength": ["Integer", 3]}, {"city": ["String", "ElPaso"], "routeColor": ["String", "wild"], "routeLength": ["Integer", 2]}]}, {"name": ["String", "Denver"], "neighbours": [{"city": ["String", "SaltLakeCity"], "routeColor": ["String", "red"], "routeLength": ["Integer", 3]}, {"city": ["String", "SaltLakeCity"], "routeColor": ["String", "yellow"], "routeLength": ["Integer", 3]}, {"city": ["String", "Helena"], "routeColor": ["String", "green"], "routeLength": ["Integer", 4]}, {"city": ["String", "Omaha"], "routeColor": ["String", "purple"], "routeLength": ["Integer", 4]}, {"city": ["String", "KansasCity"], "routeColor": ["String", "black"], "routeLength": ["Integer", 4]}, {"city": ["String", "KansasCity"], "routeColor": ["String", "orange"], "routeLength": ["Integer", 4]}, {"city": ["String", "OklahomaCity"], "routeColor": ["String", "red"], "routeLength": ["Integer", 4]}, {"city": ["String", "SantaFe"], "routeColor": ["String", "wild"], "routeLength": ["Integer", 2]}, {"city": ["String", "Phoenix"], "routeColor": ["String", "white"], "routeLength": ["Integer", 5]}]}, {"name": ["String", "OklahomaCity"], "neighbours": [{"city": ["String", "SantaFe"], "routeColor": ["String", "blue"], "routeLength": ["Integer", 3]}, {"city": ["String", "Denver"], "routeColor": ["String", "red"], "routeLength": ["Integer", 4]}, {"city": ["String", "KansasCity"], "routeColor": ["String", "wild"], "routeLength": ["Integer", 2]}, {"city": ["String", "LittleRock"], "routeColor": ["String", "wild"], "routeLength": ["Integer", 2]}, {"city": ["String", "Dallas"], "routeColor": ["String", "wild"], "routeLength": ["Integer", 2]}, {"city": ["String", "ElPaso"], "routeColor": ["String", "yellow"], "routeLength": ["Integer", 5]}]}, {"name": ["String", "ElPaso"], "neighbours": [{"city": ["String", "LosAngeles"], "routeColor": ["String", "black"], "routeLength": ["Integer", 6]}, {"city": ["String", "Phoenix"], "routeColor": ["String", "wild"], "routeLength": ["Integer", 3]}, {"city": ["String", "SantaFe"], "routeColor": ["String", "wild"], "routeLength": ["Integer", 2]}, {"city": ["String", "OklahomaCity"], "routeColor": ["String", "yellow"], "routeLength": ["Integer", 5]}, {"city": ["String", "Dallas"], "routeColor": ["String", "red"], "routeLength": ["Integer", 4]}, {"city": ["String", "Houston"], "routeColor": ["String", "green"], "routeLength": ["Integer", 6]}]}, {"name": ["String", "Dallas"], "neighbours": [{"city": ["String", "ElPaso"], "routeColor": ["String", "red"], "routeLength": ["Integer", 4]}, {"city": ["String", "OklahomaCity"], "routeColor": ["String", "wild"], "routeLength": ["Integer", 2]}, {"city": ["String", "LittleRock"], "routeColor": ["String", "wild"], "routeLength": ["Integer", 2]}, {"city": ["String", "Houston"], "routeColor": ["String", "wild"], "routeLength": ["Integer", 1]}]}, {"name": ["String", "Houston"], "neighbours": [{"city": ["String", "ElPaso"], "routeColor": ["String", "green"], "routeLength": ["Integer", 6]}, {"city": ["String", "Dallas"], "routeColor": ["String", "wild"], "routeLength": ["Integer", 1]}, {"city": ["String", "NewOrleans"], "routeColor": ["String", "wild"], "routeLength": ["Integer", 2]}]}, {"name": ["String", "KansasCity"], "neighbours": [{"city": ["String", "Denver"], "routeColor": ["String", "black"], "routeLength": ["Integer", 4]}, {"city": ["String", "Denver"], "routeColor": ["String", "orange"], "routeLength": ["Integer", 4]}, {"city": ["String", "Omaha"], "routeColor": ["String", "wild"], "routeLength": ["Integer", 1]}, {"city": ["String", "SaintLouis"], "routeColor": ["String", "blue"], "routeLength": ["Integer", 2]}, {"city": ["String", "SaintLouis"], "routeColor": ["String", "purple"], "routeLength": ["Integer", 2]}, {"city": ["String", "OklahomaCity"], "routeColor": ["String", "wild"], "routeLength": ["Integer", 2]}]}, {"name": ["String", "LittleRock"], "neighbours": [{"city": ["String", "OklahomaCity"], "routeColor": ["String", "wild"], "routeLength": ["Integer", 2]}, {"city": ["String", "SaintLouis"], "routeColor": ["String", "wild"], "routeLength": ["Integer", 2]}, {"city": ["String", "Nashville"], "routeColor": ["String", "white"], "routeLength": ["Integer", 3]}, {"city": ["String", "NewOrleans"], "routeColor": ["String", "green"], "routeLength": ["Integer", 3]}, {"city": ["String", "Dallas"], "routeColor": ["String", "wild"], "routeLength": ["Integer", 2]}]}, {"name": ["String", "NewOrleans"], "neighbours": [{"city": ["String", "Houston"], "routeColor": ["String", "wild"], "routeLength": ["Integer", 2]}, {"city": ["String", "LittleRock"], "routeColor": ["String", "green"], "routeLength": ["Integer", 3]}, {"city": ["String", "Atlanta"], "routeColor": ["String", "yellow"], "routeLength": ["Integer", 4]}, {"city": ["String", "Atlanta"], "routeColor": ["String", "orange"], "routeLength": ["Integer", 4]}, {"city": ["String", "Miami"], "routeColor": ["String", "red"], "routeLength": ["Integer", 6]}]}, {"name": ["String", "Duluth"], "neighbours": [{"city": ["String", "Helena"], "routeColor": ["String", "orange"], "routeLength": ["Integer", 6]}, {"city": ["String", "Winnipeg"], "routeColor": ["String", "black"], "routeLength": ["Integer", 4]}, {"city": ["String", "SaultStMarie"], "routeColor": ["String", "wild"], "routeLength": ["Integer", 3]}, {"city": ["String", "Toronto"], "routeColor": ["String", "purple"], "routeLength": ["Integer", 6]}, {"city": ["String", "Chicago"], "routeColor": ["String", "red"], "routeLength": ["Integer", 3]}, {"city": ["String", "Omaha"], "routeColor": ["String", "wild"], "routeLength": ["Integer", 2]}]}, {"name": ["String", "Omaha"], "neighbours": [{"city": ["String", "Helena"], "routeColor": ["String", "red"], "routeLength": ["Integer", 5]}, {"city": ["String", "Duluth"], "routeColor": ["String", "wild"], "routeLength": ["Integer", 2]}, {"city": ["String", "Chicago"], "routeColor": ["String", "blue"], "routeLength": ["Integer", 4]}, {"city": ["String", "KansasCity"], "routeColor": ["String", "wild"], "routeLength": ["Integer", 1]}, {"city": ["String", "Denver"], "routeColor": ["String", "purple"], "routeLength": ["Integer", 4]}]}, {"name": ["String", "SaintLouis"], "neighbours": [{"city": ["String", "KansasCity"], "routeColor": ["String", "purple"], "routeLength": ["Integer", 2]}, {"city": ["String", "KansasCity"], "routeColor": ["String", "blue"], "routeLength": ["Integer", 2]}, {"city": ["String", "Chicago"], "routeColor": ["String", "green"], "routeLength": ["Integer", 2]}, {"city": ["String", "Chicago"], "routeColor": ["String", "white"], "routeLength": ["Integer", 2]}, {"city": ["String", "Pittsburgh"], "routeColor": ["String", "green"], "routeLength": ["Integer", 5]}, {"city": ["String", "Nashville"], "routeColor": ["String", "wild"], "routeLength": ["Integer", 2]}, {"city": ["String", "LittleRock"], "routeColor": ["String", "wild"], "routeLength": ["Integer", 2]}]}, {"name": ["String", "Chicago"], "neighbours": [{"city": ["String", "Omaha"], "routeColor": ["String", "blue"], "routeLength": ["Integer", 4]}, {"city": ["String", "Duluth"], "routeColor": ["String", "red"], "routeLength": ["Integer", 3]}, {"city": ["String", "Toronto"], "routeColor": ["String", "white"], "routeLength": ["Integer", 4]}, {"city": ["String", "Pittsburgh"], "routeColor": ["String", "orange"], "routeLength": ["Integer", 3]}, {"city": ["String", "Pittsburgh"], "routeColor": ["String", "black"], "routeLength": ["Integer", 3]}, {"city": ["String", "SaintLouis"], "routeColor": ["String", "white"], "routeLength": ["Integer", 2]}, {"city": ["String", "SaintLouis"], "routeColor": ["String", "green"], "routeLength": ["Integer", 2]}]}, {"name": ["String", "Toronto"], "neighbours": [{"city": ["String", "Duluth"], "routeColor": ["String", "purple"], "routeLength": ["Integer", 6]}, {"city": ["String", "SaultStMarie"], "routeColor": ["String", "wild"], "routeLength": ["Integer", 2]}, {"city": ["String", "Montreal"], "routeColor": ["String", "wild"], "routeLength": ["Integer", 3]}, {"city": ["String", "Pittsburgh"], "routeColor": ["String", "wild"], "routeLength": ["Integer", 2]}, {"city": ["String", "Chicago"], "routeColor": ["String", "white"], "routeLength": ["Integer", 4]}]}, {"name": ["String", "Pittsburgh"], "neighbours": [{"city": ["String", "Chicago"], "routeColor": ["String", "black"], "routeLength": ["Integer", 3]}, {"city": ["String", "Chicago"], "routeColor": ["String", "orange"], "routeLength": ["Integer", 3]}, {"city": ["String", "Toronto"], "routeColor": ["String", "wild"], "routeLength": ["Integer", 2]}, {"city": ["String", "NewYork"], "routeColor": ["String", "white"], "routeLength": ["Integer", 2]}, {"city": ["String", "NewYork"], "routeColor": ["String", "green"], "routeLength": ["Integer", 2]}, {"city": ["String", "Washington"], "routeColor": ["String", "wild"], "routeLength": ["Integer", 2]}, {"city": ["String", "Raleigh"], "routeColor": ["String", "wild"], "routeLength": ["Integer", 2]}, {"city": ["String", "Nashville"], "routeColor": ["String", "yellow"], "routeLength": ["Integer", 4]}, {"city": ["String", "SaintLouis"], "routeColor": ["String", "green"], "routeLength": ["Integer", 5]}]}, {"name": ["String", "Nashville"], "neighbours": [{"city": ["String", "SaintLouis"], "routeColor": ["String", "wild"], "routeLength": ["Integer", 2]}, {"city": ["String", "Pittsburgh"], "routeColor": ["String", "yellow"], "routeLength": ["Integer", 4]}, {"city": ["String", "Raleigh"], "routeColor": ["String", "black"], "routeLength": ["Integer", 3]}, {"city": ["String", "Atlanta"], "routeColor": ["String", "wild"], "routeLength": ["Integer", 1]}, {"city": ["String", "LittleRock"], "routeColor": ["String", "white"], "routeLength": ["Integer", 3]}]}, {"name": ["String", "Raleigh"], "neighbours": [{"city": ["String", "Nashville"], "routeColor": ["String", "black"], "routeLength": ["Integer", 3]}, {"city": ["String", "Pittsburgh"], "routeColor": ["String", "wild"], "routeLength": ["Integer", 2]}, {"city": ["String", "Washington"], "routeColor": ["String", "wild"], "routeLength": ["Integer", 2]}, {"city": ["String", "Charleston"], "routeColor": ["String", "wild"], "routeLength": ["Integer", 2]}, {"city": ["String", "Atlanta"], "routeColor": ["String", "wild"], "routeLength": ["Integer", 2]}]}, {"name": ["String", "Atlanta"], "neighbours": [{"city": ["String", "Nashville"], "routeColor": ["String", "wild"], "routeLength": ["Integer", 1]}, {"city": ["String", "Raleigh"], "routeColor": ["String", "wild"], "routeLength": ["Integer", 2]}, {"city": ["String", "Charleston"], "routeColor": ["String", "wild"], "routeLength": ["Integer", 2]}, {"city": ["String", "Miami"], "routeColor": ["String", "blue"], "routeLength": ["Integer", 5]}, {"city": ["String", "NewOrleans"], "routeColor": ["String", "orange"], "routeLength": ["Integer", 4]}, {"city": ["String", "NewOrleans"], "routeColor": ["String", "yellow"], "routeLength": ["Integer", 4]}]}, {"name": ["String", "Miami"], "neighbours": [{"city": ["String", "NewOrleans"], "routeColor": ["String", "red"], "routeLength": ["Integer", 6]}, {"city": ["String", "Atlanta"], "routeColor": ["String", "blue"], "routeLength": ["Integer", 5]}, {"city": ["String", "Charleston"], "routeColor": ["String", "purple"], "routeLength": ["Integer", 4]}]}, {"name": ["String", "Charleston"], "neighbours": [{"city": ["String", "Atlanta"], "routeColor": ["String", "wild"], "routeLength": ["Integer", 2]}, {"city": ["String", "Raleigh"], "routeColor": ["String", "wild"], "routeLength": ["Integer", 2]}, {"city": ["String", "Miami"], "routeColor": ["String", "purple"], "routeLength": ["Integer", 4]}]}, {"name": ["String", "Washington"], "neighbours": [{"city": ["String", "Pittsburgh"], "routeColor": ["String", "wild"], "routeLength": ["Integer", 2]}, {"city": ["String", "NewYork"], "routeColor": ["String", "orange"], "routeLength": ["Integer", 2]}, {"city": ["String", "NewYork"], "routeColor": ["String", "black"], "routeLength": ["Integer", 2]}, {"city": ["String", "Raleigh"], "routeColor": ["String", "wild"], "routeLength": ["Integer", 2]}]}, {"name": ["String", "NewYork"], "neighbours": [{"city": ["String", "Montreal"], "routeColor": ["String", "blue"], "routeLength": ["Integer", 3]}, {"city": ["String", "Boston"], "routeColor": ["String", "yellow"], "routeLength": ["Integer", 2]}, {"city": ["String", "Boston"], "routeColor": ["String", "red"], "routeLength": ["Integer", 2]}, {"city": ["String", "Washington"], "routeColor": ["String", "black"], "routeLength": ["Integer", 2]}, {"city": ["String", "Washington"], "routeColor": ["String", "orange"], "routeLength": ["Integer", 2]}, {"city": ["String", "Pittsburgh"], "routeColor": ["String", "green"], "routeLength": ["Integer", 2]}, {"city": ["String", "Pittsburgh"], "routeColor": ["String", "white"], "routeLength": ["Integer", 2]}]}, {"name": ["String", "Boston"], "neighbours": [{"city": ["String", "Montreal"], "routeColor": ["String", "wild"], "routeLength": ["Integer", 2]}, {"city": ["String", "NewYork"], "routeColor": ["String", "red"], "routeLength": ["Integer", 2]}, {"city": ["String", "NewYork"], "routeColor": ["String", "yellow"], "routeLength": ["Integer", 2]}]}]}